[
  {
    "line": 1,
    "elements": [
      {
        "start_timestamp": "2020-04-06T23:34:33.034Z",
        "line": 14,
        "name": "Verify if Place is being succesfully added using AddPlaceAPI",
        "description": "",
        "id": "validating-place-api-s;verify-if-place-is-being-succesfully-added-using-addplaceapi;;2",
        "type": "scenario",
        "keyword": "Scenario Outline",
        "steps": [
          {
            "result": {
              "duration": 1305000000,
              "status": "passed"
            },
            "line": 5,
            "name": "Add place Payload with \"AHouse\" \"English\" \"World cross center\"",
            "match": {
              "arguments": [
                {
                  "val": "\"AHouse\"",
                  "offset": 23
                },
                {
                  "val": "\"English\"",
                  "offset": 32
                },
                {
                  "val": "\"World cross center\"",
                  "offset": 42
                }
              ],
              "location": "stepDefinitions.PlaceValidationSteps.add_place_Payload(java.lang.String,java.lang.String,java.lang.String)"
            },
            "keyword": "Given "
          },
          {
            "result": {
              "duration": 3624000000,
              "status": "passed"
            },
            "line": 6,
            "name": "User calls \"addPlaceAPI\" with \"Post\" http request",
            "match": {
              "arguments": [
                {
                  "val": "\"addPlaceAPI\"",
                  "offset": 11
                },
                {
                  "val": "\"Post\"",
                  "offset": 30
                }
              ],
              "location": "stepDefinitions.PlaceValidationSteps.user_calls_with_http_request(java.lang.String,java.lang.String)"
            },
            "keyword": "When "
          },
          {
            "result": {
              "duration": 3000000,
              "status": "passed"
            },
            "line": 7,
            "name": "the Api call got success with status code 200",
            "match": {
              "arguments": [
                {
                  "val": "200",
                  "offset": 42
                }
              ],
              "location": "stepDefinitions.PlaceValidationSteps.the_Api_call_got_success_with_status_code(java.lang.Integer)"
            },
            "keyword": "Then "
          },
          {
            "result": {
              "duration": 379000000,
              "status": "passed"
            },
            "line": 8,
            "name": "\"status\" in response body is \"OK\"",
            "match": {
              "arguments": [
                {
                  "val": "\"status\"",
                  "offset": 0
                },
                {
                  "val": "\"OK\"",
                  "offset": 29
                }
              ],
              "location": "stepDefinitions.PlaceValidationSteps.in_response_body_is(java.lang.String,java.lang.String)"
            },
            "keyword": "And "
          },
          {
            "result": {
              "duration": 9000000,
              "status": "passed"
            },
            "line": 9,
            "name": "\"scope\" in response body is \"APP\"",
            "match": {
              "arguments": [
                {
                  "val": "\"scope\"",
                  "offset": 0
                },
                {
                  "val": "\"APP\"",
                  "offset": 28
                }
              ],
              "location": "stepDefinitions.PlaceValidationSteps.in_response_body_is(java.lang.String,java.lang.String)"
            },
            "keyword": "And "
          },
          {
            "result": {
              "duration": 2093000000,
              "status": "passed"
            },
            "line": 10,
            "name": "verify place_id created maps to \"AHouse\" using \"getPlaceAPI\"",
            "match": {
              "arguments": [
                {
                  "val": "\"AHouse\"",
                  "offset": 32
                },
                {
                  "val": "\"getPlaceAPI\"",
                  "offset": 47
                }
              ],
              "location": "stepDefinitions.PlaceValidationSteps.verify_place_id_created_maps_to_using(java.lang.String,java.lang.String)"
            },
            "keyword": "And "
          }
        ],
        "tags": [
          {
            "name": "@AddPlace"
          },
          {
            "name": "@Regression"
          }
        ]
      },
      {
        "start_timestamp": "2020-04-06T23:34:40.548Z",
        "line": 15,
        "name": "Verify if Place is being succesfully added using AddPlaceAPI",
        "description": "",
        "id": "validating-place-api-s;verify-if-place-is-being-succesfully-added-using-addplaceapi;;3",
        "type": "scenario",
        "keyword": "Scenario Outline",
        "steps": [
          {
            "result": {
              "duration": 9000000,
              "status": "passed"
            },
            "line": 5,
            "name": "Add place Payload with \"Crystal Palace\" \"PT-BR\" \"Build SP\"",
            "match": {
              "arguments": [
                {
                  "val": "\"Crystal Palace\"",
                  "offset": 23
                },
                {
                  "val": "\"PT-BR\"",
                  "offset": 40
                },
                {
                  "val": "\"Build SP\"",
                  "offset": 48
                }
              ],
              "location": "stepDefinitions.PlaceValidationSteps.add_place_Payload(java.lang.String,java.lang.String,java.lang.String)"
            },
            "keyword": "Given "
          },
          {
            "result": {
              "duration": 1998000000,
              "status": "passed"
            },
            "line": 6,
            "name": "User calls \"addPlaceAPI\" with \"Post\" http request",
            "match": {
              "arguments": [
                {
                  "val": "\"addPlaceAPI\"",
                  "offset": 11
                },
                {
                  "val": "\"Post\"",
                  "offset": 30
                }
              ],
              "location": "stepDefinitions.PlaceValidationSteps.user_calls_with_http_request(java.lang.String,java.lang.String)"
            },
            "keyword": "When "
          },
          {
            "result": {
              "duration": 1000000,
              "status": "passed"
            },
            "line": 7,
            "name": "the Api call got success with status code 200",
            "match": {
              "arguments": [
                {
                  "val": "200",
                  "offset": 42
                }
              ],
              "location": "stepDefinitions.PlaceValidationSteps.the_Api_call_got_success_with_status_code(java.lang.Integer)"
            },
            "keyword": "Then "
          },
          {
            "result": {
              "duration": 9000000,
              "status": "passed"
            },
            "line": 8,
            "name": "\"status\" in response body is \"OK\"",
            "match": {
              "arguments": [
                {
                  "val": "\"status\"",
                  "offset": 0
                },
                {
                  "val": "\"OK\"",
                  "offset": 29
                }
              ],
              "location": "stepDefinitions.PlaceValidationSteps.in_response_body_is(java.lang.String,java.lang.String)"
            },
            "keyword": "And "
          },
          {
            "result": {
              "status": "passed"
            },
            "line": 9,
            "name": "\"scope\" in response body is \"APP\"",
            "match": {
              "arguments": [
                {
                  "val": "\"scope\"",
                  "offset": 0
                },
                {
                  "val": "\"APP\"",
                  "offset": 28
                }
              ],
              "location": "stepDefinitions.PlaceValidationSteps.in_response_body_is(java.lang.String,java.lang.String)"
            },
            "keyword": "And "
          },
          {
            "result": {
              "duration": 1923000000,
              "status": "passed"
            },
            "line": 10,
            "name": "verify place_id created maps to \"Crystal Palace\" using \"getPlaceAPI\"",
            "match": {
              "arguments": [
                {
                  "val": "\"Crystal Palace\"",
                  "offset": 32
                },
                {
                  "val": "\"getPlaceAPI\"",
                  "offset": 55
                }
              ],
              "location": "stepDefinitions.PlaceValidationSteps.verify_place_id_created_maps_to_using(java.lang.String,java.lang.String)"
            },
            "keyword": "And "
          }
        ],
        "tags": [
          {
            "name": "@AddPlace"
          },
          {
            "name": "@Regression"
          }
        ]
      }
    ],
    "name": "Validating Place API\u0027s",
    "description": "",
    "id": "validating-place-api-s",
    "keyword": "Feature",
    "uri": "file:src/test/java/features/placeValidations.feature",
    "tags": []
  }
]